flask_restx_extended/__about__.py
flask_restx_extended/__init__.py
flask_restx_extended/_http.py
flask_restx_extended/api.py
flask_restx_extended/apidoc.py
flask_restx_extended/cors.py
flask_restx_extended/errors.py
flask_restx_extended/fields.py
flask_restx_extended/inputs.py
flask_restx_extended/marshalling.py
flask_restx_extended/mask.py
flask_restx_extended/model.py
flask_restx_extended/namespace.py
flask_restx_extended/postman.py
flask_restx_extended/representations.py
flask_restx_extended/reqparse.py
flask_restx_extended/resource.py
flask_restx_extended/swagger.py
flask_restx_extended/utils.py
flask_restx_extended/schemas/__init__.py
flask_restx_extended/schemas/oas-2.0.json
flask_restx_extended/templates/swagger-ui-css.html
flask_restx_extended/templates/swagger-ui-libs.html
flask_restx_extended/templates/swagger-ui.html
flask_restx_extended-0.5.2.dist-info/LICENSE
flask_restx_extended-0.5.2.dist-info/METADATA
flask_restx_extended-0.5.2.dist-info/WHEEL
flask_restx_extended-0.5.2.dist-info/top_level.txt
flask_restx_extended-0.5.2.dist-info/RECORD
