Metadata-Version: 2.1
Name: flask-restx-extended
Version: 0.5.2
Summary: Fixed Reverse Proxy Swagger Error of Restx
Home-page: https://github.com/seeodm/flask-restx-extended
Author: Dongmin Seo
License: BSD-3-Clause
Keywords: flask restx rest api swagger openapi
Platform: UNKNOWN
Classifier: Development Status :: 3 - Alpha
Classifier: Programming Language :: Python
Classifier: Environment :: Web Environment
Classifier: Operating System :: OS Independent
Classifier: Intended Audience :: Developers
Classifier: Topic :: System :: Software Distribution
Classifier: Programming Language :: Python
Classifier: Programming Language :: Python :: 2
Classifier: Programming Language :: Python :: 2.7
Classifier: Programming Language :: Python :: 3
Classifier: Programming Language :: Python :: 3.5
Classifier: Programming Language :: Python :: 3.6
Classifier: Programming Language :: Python :: 3.7
Classifier: Programming Language :: Python :: 3.8
Classifier: Programming Language :: Python :: Implementation :: PyPy
Classifier: Topic :: Software Development :: Libraries :: Python Modules
Classifier: License :: OSI Approved :: BSD License
Requires-Dist: jsonschema
Requires-Dist: Flask (<2.0.0,>=0.8)
Requires-Dist: werkzeug (<2.0.0)
Requires-Dist: pytz
Requires-Dist: six (>=1.3.0)
Requires-Dist: enum34 ; python_version < "3.4"
Requires-Dist: aniso8601 (==8.0.0) ; python_version < "3.5"
Requires-Dist: aniso8601 (>=0.82) ; python_version >= "3.5"
Provides-Extra: dev
Requires-Dist: blinker ; extra == 'dev'
Requires-Dist: Faker (==2.0.0) ; extra == 'dev'
Requires-Dist: mock (==3.0.5) ; extra == 'dev'
Requires-Dist: pytest-benchmark (==3.2.2) ; extra == 'dev'
Requires-Dist: pytest-cov (==2.7.1) ; extra == 'dev'
Requires-Dist: pytest-flask (==0.15.1) ; extra == 'dev'
Requires-Dist: pytest-mock (==1.10.4) ; extra == 'dev'
Requires-Dist: pytest-profiling (==1.7.0) ; extra == 'dev'
Requires-Dist: tzlocal ; extra == 'dev'
Requires-Dist: invoke (==1.3.0) ; extra == 'dev'
Requires-Dist: readme-renderer (==24.0) ; extra == 'dev'
Requires-Dist: twine (==1.15.0) ; extra == 'dev'
Requires-Dist: tox ; extra == 'dev'
Requires-Dist: pytest (==4.6.5) ; (python_version < "3.5") and extra == 'dev'
Requires-Dist: pytest (==5.4.1) ; (python_version >= "3.5") and extra == 'dev'
Requires-Dist: ossaudit ; (python_version >= "3.5") and extra == 'dev'
Requires-Dist: black ; (python_version >= "3.6") and extra == 'dev'
Provides-Extra: doc
Requires-Dist: alabaster (==0.7.12) ; extra == 'doc'
Requires-Dist: Sphinx (==2.1.2) ; extra == 'doc'
Requires-Dist: sphinx-issues (==1.2.0) ; extra == 'doc'
Provides-Extra: test
Requires-Dist: blinker ; extra == 'test'
Requires-Dist: Faker (==2.0.0) ; extra == 'test'
Requires-Dist: mock (==3.0.5) ; extra == 'test'
Requires-Dist: pytest-benchmark (==3.2.2) ; extra == 'test'
Requires-Dist: pytest-cov (==2.7.1) ; extra == 'test'
Requires-Dist: pytest-flask (==0.15.1) ; extra == 'test'
Requires-Dist: pytest-mock (==1.10.4) ; extra == 'test'
Requires-Dist: pytest-profiling (==1.7.0) ; extra == 'test'
Requires-Dist: tzlocal ; extra == 'test'
Requires-Dist: invoke (==1.3.0) ; extra == 'test'
Requires-Dist: readme-renderer (==24.0) ; extra == 'test'
Requires-Dist: twine (==1.15.0) ; extra == 'test'
Requires-Dist: pytest (==4.6.5) ; (python_version < "3.5") and extra == 'test'
Requires-Dist: pytest (==5.4.1) ; (python_version >= "3.5") and extra == 'test'
Requires-Dist: ossaudit ; (python_version >= "3.5") and extra == 'test'
